UicCs385CaozuoxitongJiangyi/README.md
UicCs385CaozuoxitongJiangyi/__init__.py
UicCs385CaozuoxitongJiangyi/__main__.py
UicCs385CaozuoxitongJiangyi/file.epub
UicCs385CaozuoxitongJiangyi/index.html
UicCs385CaozuoxitongJiangyi/css/__init__.py
UicCs385CaozuoxitongJiangyi/css/annotations.css
UicCs385CaozuoxitongJiangyi/css/main.css
UicCs385CaozuoxitongJiangyi/css/normalize.css
UicCs385CaozuoxitongJiangyi/css/popup.css
UicCs385CaozuoxitongJiangyi/font/__init__.py
UicCs385CaozuoxitongJiangyi/font/fontello.eot
UicCs385CaozuoxitongJiangyi/font/fontello.svg
UicCs385CaozuoxitongJiangyi/font/fontello.ttf
UicCs385CaozuoxitongJiangyi/font/fontello.woff
UicCs385CaozuoxitongJiangyi/img/__init__.py
UicCs385CaozuoxitongJiangyi/img/annotator-glyph-sprite.png
UicCs385CaozuoxitongJiangyi/img/annotator-icon-sprite.png
UicCs385CaozuoxitongJiangyi/img/apple-touch-icon.png
UicCs385CaozuoxitongJiangyi/img/cancelfullscreen.png
UicCs385CaozuoxitongJiangyi/img/close.png
UicCs385CaozuoxitongJiangyi/img/fullscreen.png
UicCs385CaozuoxitongJiangyi/img/loader.gif
UicCs385CaozuoxitongJiangyi/img/menu-icon.png
UicCs385CaozuoxitongJiangyi/img/save.png
UicCs385CaozuoxitongJiangyi/img/saved.png
UicCs385CaozuoxitongJiangyi/img/settings-s.png
UicCs385CaozuoxitongJiangyi/img/settings.png
UicCs385CaozuoxitongJiangyi/img/star.png
UicCs385CaozuoxitongJiangyi/js/__init__.py
UicCs385CaozuoxitongJiangyi/js/epub.js
UicCs385CaozuoxitongJiangyi/js/epub.min.js
UicCs385CaozuoxitongJiangyi/js/epub.min.map
UicCs385CaozuoxitongJiangyi/js/hooks.min.js
UicCs385CaozuoxitongJiangyi/js/hooks.min.map
UicCs385CaozuoxitongJiangyi/js/reader.js
UicCs385CaozuoxitongJiangyi/js/reader.js.map
UicCs385CaozuoxitongJiangyi/js/reader.min.js
UicCs385CaozuoxitongJiangyi/js/reader.min.map
UicCs385CaozuoxitongJiangyi/js/hooks/__init__.py
UicCs385CaozuoxitongJiangyi/js/hooks/extensions/__init__.py
UicCs385CaozuoxitongJiangyi/js/hooks/extensions/highlight.js
UicCs385CaozuoxitongJiangyi/js/libs/__init__.py
uic_cs385_caozuoxitong_jiangyi-2024.3.4.0.dist-info/METADATA
uic_cs385_caozuoxitong_jiangyi-2024.3.4.0.dist-info/WHEEL
uic_cs385_caozuoxitong_jiangyi-2024.3.4.0.dist-info/entry_points.txt
uic_cs385_caozuoxitong_jiangyi-2024.3.4.0.dist-info/top_level.txt
uic_cs385_caozuoxitong_jiangyi-2024.3.4.0.dist-info/RECORD
